choicelib/__init__.py
choicelib/choicelib.py
choicelib/order.py
choicelib-0.1.4.dist-info/LICENSE
choicelib-0.1.4.dist-info/WHEEL
choicelib-0.1.4.dist-info/METADATA
choicelib-0.1.4.dist-info/RECORD
